MANIFEST.in
README.md
acoewidgets.json
event.json
setup.cfg
setup.py
acoewidgets/__init__.py
acoewidgets/_version.py
acoewidgets/endpoint.py
acoewidgets/event.json
acoewidgets.egg-info/PKG-INFO
acoewidgets.egg-info/SOURCES.txt
acoewidgets.egg-info/dependency_links.txt
acoewidgets.egg-info/not-zip-safe
acoewidgets.egg-info/requires.txt
acoewidgets.egg-info/top_level.txt
acoewidgets/static/event.json
acoewidgets/static/extension.js
acoewidgets/static/index.js
acoewidgets/static/index.js.map